Metadata-Version: 1.1
Name: gurka-toolkits
Version: 0.1
Summary: Contains a set of helper kits that can help you for development.
Home-page: http://github.com/yanwarsolah/gurka_toolkits
Author: Yanwar Solahudin
Author-email: yanwarsolah@gmail.com
License: MIT
Platform: UNKNOWN
Classifier: Development Status :: 2 - Pre-Alpha
Classifier: License :: OSI Approved :: MIT License
Classifier: Programming Language :: Python :: 2.7
Classifier: Programming Language :: Python :: 3.4
Classifier: Programming Language :: Python :: 3.5
Classifier: Programming Language :: Python :: 3.6
Classifier: Topic :: Software Development :: Libraries
